lotr_sdk/Session.py
lotr_sdk/__init__.py
lotr_sdk/conf.py
lotr_sdk/mixins.py
lotr_sdk/sdk.py
jackofspades_lib_lab_lotr-0.1.1.dist-info/LICENSE.txt
jackofspades_lib_lab_lotr-0.1.1.dist-info/METADATA
jackofspades_lib_lab_lotr-0.1.1.dist-info/WHEEL
jackofspades_lib_lab_lotr-0.1.1.dist-info/top_level.txt
jackofspades_lib_lab_lotr-0.1.1.dist-info/RECORD
