Metadata-Version: 2.1
Name: jackofspades-lib-lab-lotr
Version: 0.1.1
Author: JackofSpades707
Author-email: JackofSpades707@hotmail.com
License: MIT
Classifier: Programming Language :: Python :: 3
Classifier: License :: OSI Approved :: MIT License
Classifier: Operating System :: OS Independent
License-File: LICENSE.txt
Requires-Dist: requests
